fivetran/__init__.py
fivetran/fivetran_request.py
fivetran/fivetran_response.py
aps_cloud_util-0.1.0.dist-info/METADATA
aps_cloud_util-0.1.0.dist-info/WHEEL
aps_cloud_util-0.1.0.dist-info/top_level.txt
aps_cloud_util-0.1.0.dist-info/RECORD
