Metadata-Version: 2.1
Name: aps-cloud-util
Version: 0.1.0
Summary: A short description of your package
Home-page: https://github.com/yourusername/your-package-name
Author: Joe Chevalier
Author-email: jchevalier@apspayroll.com
Classifier: Programming Language :: Python :: 3
Classifier: License :: OSI Approved :: MIT License
Classifier: Operating System :: OS Independent
Requires-Python: >=3.11
